{
    "configurations": [
        {
            "name": "Linux",
            "includePath": [
                "${workspaceFolder}/**",
                "${workspaceFolder}/include",
                "/usr/local/include/rest_rpc/include",
                "/usr/local/include/rest_rpc/include/rest_rpc",
                "/usr/local/include/pybind11",
                "/usr/include/python3.10",
                "/usr/local/include",
                "${workspaceFolder}/test",
                "/usr/lib/gcc/x86_64-linux-gnu/12/include"
            ],
            "defines": [],
            "compilerPath": "/usr/bin/clang",
            "cStandard": "c17",
            "intelliSenseMode": "linux-clang-x64",
            "configurationProvider": "ms-vscode.cmake-tools",
            "cppStandard": "c++17"
        }
    ],
    "version": 4
}